ihttpy/__init__.py
ihttpy/defenitions.py
ihttpy/httpserver.py
ihttpy/utils.py
ihttpy/exceptions/__init__.py
ihttpy/exceptions/errors.py
ihttpy/exceptions/logger.py
ihttpy/requests/__init__.py
ihttpy/requests/methods.py
ihttpy/requests/request.py
ihttpy/requests/response.py
ihttpy/requests/sender.py
ihttpy/routing/__init__.py
ihttpy/routing/configurator.py
ihttpy/routing/page.py
ihttpy/routing/router.py
ihttpy-2.1.0.dist-info/LICENSE
ihttpy-2.1.0.dist-info/METADATA
ihttpy-2.1.0.dist-info/WHEEL
ihttpy-2.1.0.dist-info/top_level.txt
ihttpy-2.1.0.dist-info/RECORD
