Metadata-Version: 2.1
Name: ihttpy
Version: 2.1.0
Summary: A http server with fluent interface decorators, and plain text configuration
Home-page: https://github.com/irusland/httpserver
Author: irusland
Author-email: ruslansir@icloud.com
License: UNKNOWN
Platform: UNKNOWN
Classifier: Programming Language :: Python :: 3
Classifier: License :: OSI Approved :: MIT License
Classifier: Operating System :: OS Independent
Requires-Python: >=3.6
License-File: LICENSE
Requires-Dist: certifi (==2020.12.5)
Requires-Dist: chardet (==4.0.0)
Requires-Dist: diskcache (==5.2.1)
Requires-Dist: dnspython (==2.1.0)
Requires-Dist: pip (==21.0.1)
Requires-Dist: pymongo (==3.11.3)
Requires-Dist: python-magic (==0.4.18)
Requires-Dist: wheel (==0.36.2)
Requires-Dist: py-flags (==1.1.4)
